workday_calc/__init__.py
workday_calc/cli.py
workday_calc-1.0.8.dist-info/licenses/LICENSE
workday_calc-1.0.8.dist-info/METADATA
workday_calc-1.0.8.dist-info/WHEEL
workday_calc-1.0.8.dist-info/entry_points.txt
workday_calc-1.0.8.dist-info/top_level.txt
workday_calc-1.0.8.dist-info/RECORD
