Metadata-Version: 2.4
Name: workday-calc
Version: 1.0.8
Summary: pyproject.tomlのテスト
Home-page: https://github.com/konono/workday-calc
Author: kon0n0
Author-email: kono@ms1.kononet.jp
License: MIT
Classifier: Development Status :: 4 - Beta
Classifier: License :: OSI Approved :: MIT License
Classifier: Programming Language :: Python :: 3.7
Classifier: Programming Language :: Python :: 3.8
Classifier: Programming Language :: Python :: 3.9
Classifier: Programming Language :: Python :: 3.10
Classifier: Programming Language :: Python :: 3.11
Requires-Python: >=3.7
License-File: LICENSE
Requires-Dist: scikit-learn
Requires-Dist: argparse
Requires-Dist: arrow
Requires-Dist: datetime
Requires-Dist: jpholiday
Requires-Dist: workdays
Dynamic: license-file
